odoo/addons/account_reconcile_payment_order/README.rst
odoo/addons/account_reconcile_payment_order/__init__.py
odoo/addons/account_reconcile_payment_order/__manifest__.py
odoo/addons/account_reconcile_payment_order/i18n/account_reconcile_payment_order.pot
odoo/addons/account_reconcile_payment_order/i18n/de.po
odoo/addons/account_reconcile_payment_order/i18n/fr.po
odoo/addons/account_reconcile_payment_order/i18n/it.po
odoo/addons/account_reconcile_payment_order/i18n/nl_NL.po
odoo/addons/account_reconcile_payment_order/i18n/sl.po
odoo/addons/account_reconcile_payment_order/models/__init__.py
odoo/addons/account_reconcile_payment_order/models/account_bank_statement_line.py
odoo/addons/account_reconcile_payment_order/readme/CONFIGURE.rst
odoo/addons/account_reconcile_payment_order/readme/CONTRIBUTORS.rst
odoo/addons/account_reconcile_payment_order/readme/DESCRIPTION.rst
odoo/addons/account_reconcile_payment_order/readme/INSTALL.rst
odoo/addons/account_reconcile_payment_order/readme/ROADMAP.rst
odoo/addons/account_reconcile_payment_order/readme/USAGE.rst
odoo/addons/account_reconcile_payment_order/static/description/icon.png
odoo/addons/account_reconcile_payment_order/static/description/index.html
odoo/addons/account_reconcile_payment_order/tests/__init__.py
odoo/addons/account_reconcile_payment_order/tests/test_account_reconcile_payment_order.py
odoo11_addon_account_reconcile_payment_order-11.0.1.0.0.99.dev3.dist-info/METADATA
odoo11_addon_account_reconcile_payment_order-11.0.1.0.0.99.dev3.dist-info/WHEEL
odoo11_addon_account_reconcile_payment_order-11.0.1.0.0.99.dev3.dist-info/top_level.txt
odoo11_addon_account_reconcile_payment_order-11.0.1.0.0.99.dev3.dist-info/RECORD
